wraps/__init__.py
wraps/either.py
wraps/errors.py
wraps/iters.py
wraps/markers.py
wraps/option.py
wraps/panics.py
wraps/py.typed
wraps/reprs.py
wraps/result.py
wraps/typing.py
wraps/early/__init__.py
wraps/early/decorators.py
wraps/early/errors.py
wraps/futures/__init__.py
wraps/futures/either.py
wraps/futures/future.py
wraps/futures/option.py
wraps/futures/reawaitable.py
wraps/futures/result.py
wraps/futures/typing.py
wraps/parse/__init__.py
wraps/parse/format.py
wraps/parse/normal.py
wraps/parse/simple.py
wraps-0.14.1.dist-info/METADATA
wraps-0.14.1.dist-info/WHEEL
wraps-0.14.1.dist-info/licenses/LICENSE
wraps-0.14.1.dist-info/RECORD
